ConfigEnv/Config.py
ConfigEnv/FileFormatException.py
ConfigEnv/__init__.py
ConfigEnv-1.0.0.dist-info/METADATA
ConfigEnv-1.0.0.dist-info/RECORD
ConfigEnv-1.0.0.dist-info/WHEEL
ConfigEnv-1.0.0.dist-info/top_level.txt
