Metadata-Version: 2.1
Name: ConfigEnv
Version: 1.0.0
Summary: Gestionnaire de configuration en json, ini avec overide possible en variable d’environnement
Home-page: https://github.com/Nydareld/ConfigEnv
Author: Théo "Nydareld" Guerin
Author-email: theo.guerin.pro@gmail.com
License: UNKNOWN
Platform: UNKNOWN
Classifier: Programming Language :: Python :: 3.5
Classifier: License :: OSI Approved :: MIT License
Classifier: Operating System :: OS Independent
